clnews
