Metadata-Version: 1.0
Name: clnews
Version: 0.4.0
Summary: Advanced news feed reader
Home-page: https://github.com/antavelos/clnews
Author: Alexandros Ntavelos
Author-email: a.ntavelos@gmail.com
License: LICENSE.txt
Platform: UNKNOWN
